speaking/__init__.py
speaking/speek.py
speakdis-0.0.11.dist-info/LICENSE
speakdis-0.0.11.dist-info/METADATA
speakdis-0.0.11.dist-info/WHEEL
speakdis-0.0.11.dist-info/top_level.txt
speakdis-0.0.11.dist-info/RECORD
