Metadata-Version: 2.1
Name: speakdis
Version: 0.0.11
Summary: small description
Home-page: UNKNOWN
Author: Jerry4539
Author-email: <shanayaagraval@gmail.com>
License: UNKNOWN
Platform: UNKNOWN
Classifier: Development Status :: 1 - Planning
Classifier: Intended Audience :: Developers
Classifier: Programming Language :: Python :: 3
Classifier: Operating System :: Unix
Classifier: Operating System :: MacOS :: MacOS X
Classifier: Operating System :: Microsoft :: Windows
License-File: LICENSE
Requires-Dist: pyttsx3
Requires-Dist: colorama
